codegenai/README.md
codegenai/__init__.py
codegenai/aids.py
codegenai/cn.py
codegenai/licence.txt
codegenai/main.py
codegenai/special.py
codegenai/data/AIDS.ipynb
codegenai/data/ANOVA Test.ipynb
codegenai/data/All.ipynb
codegenai/data/AlphaBetaPruning.ipynb
codegenai/data/Astar.ipynb
codegenai/data/BFS.ipynb
codegenai/data/CSP House Allocation.ipynb
codegenai/data/CSP Map Coloring.ipynb
codegenai/data/DFS.ipynb
codegenai/data/DLS.ipynb
codegenai/data/Everything.ipynb
codegenai/data/Genetic.ipynb
codegenai/data/IDAstar.ipynb
codegenai/data/IDS.ipynb
codegenai/data/Linear Regression.ipynb
codegenai/data/Logistic Regression.ipynb
codegenai/data/Random Sampling.ipynb
codegenai/data/SMAstar.ipynb
codegenai/data/Simulated Annealing.ipynb
codegenai/data/Sudoku.ipynb
codegenai/data/T Test.ipynb
codegenai/data/UCS.ipynb
codegenai/data/Z Test.ipynb
codegenai/data/demo.ipynb
codegenai/data/height_weight_bmi.csv
codegenai/data/hours_scores_records.csv
codegenai/data/sample_data.csv
codegenai/data/testing.ipynb
codegenai/data/AIDS CN/Ubuntu CN Lab.iso
codegenai/data/AIDS CN/AIDS/1. Implement Basic Search Strategies/(A) Breadth First Search.ipynb
codegenai/data/AIDS CN/AIDS/1. Implement Basic Search Strategies/(B) Depth First Search.ipynb
codegenai/data/AIDS CN/AIDS/1. Implement Basic Search Strategies/(C) Uniform Cost Search.ipynb
codegenai/data/AIDS CN/AIDS/1. Implement Basic Search Strategies/(D) Depth Limites Search.ipynb
codegenai/data/AIDS CN/AIDS/1. Implement Basic Search Strategies/(E) Iterative Deepening DFS.ipynb
codegenai/data/AIDS CN/AIDS/10. ANOVA/2_ANOVA.csv
codegenai/data/AIDS CN/AIDS/10. ANOVA/One Way ANOVA (Repeated Measure).ipynb
codegenai/data/AIDS CN/AIDS/10. ANOVA/One Way ANOVA.ipynb
codegenai/data/AIDS CN/AIDS/10. ANOVA/Sample 1 Way ANOVA Test.ipynb
codegenai/data/AIDS CN/AIDS/10. ANOVA/Two Way ANOVA.ipynb
codegenai/data/AIDS CN/AIDS/10. ANOVA/reaction_time.csv
codegenai/data/AIDS CN/AIDS/10. ANOVA/sample_data.csv
codegenai-6.3.dist-info/METADATA
codegenai-6.3.dist-info/WHEEL
codegenai-6.3.dist-info/top_level.txt
codegenai-6.3.dist-info/RECORD
