Metadata-Version: 2.1
Name: codegenai
Version: 6.3
Summary: AI Algorithms And Computer Network Related Code
Author: Anonymus
Requires-Dist: networkx
Requires-Dist: matplotlib
Requires-Dist: tqdm
Requires-Dist: numpy
Requires-Dist: scipy
Requires-Dist: scikit-learn
Requires-Dist: seaborn
